scared/__init__.py
scared/_version.py
scared/container.py
scared/discriminants.py
scared/models.py
scared/scared.py
scared/synchronization.py
scared/ttest.py
scared/aes/__init__.py
scared/aes/base.py
scared/aes/selection_functions/__init__.py
scared/aes/selection_functions/decrypt.py
scared/aes/selection_functions/encrypt.py
scared/analysis/__init__.py
scared/analysis/_analysis.py
scared/analysis/base.py
scared/analysis/template.py
scared/des/__init__.py
scared/des/base.py
scared/des/selection_functions/__init__.py
scared/des/selection_functions/decrypt.py
scared/des/selection_functions/encrypt.py
scared/distinguishers/__init__.py
scared/distinguishers/base.py
scared/distinguishers/cpa.py
scared/distinguishers/dpa.py
scared/distinguishers/mia.py
scared/distinguishers/partitioned.py
scared/distinguishers/template.py
scared/preprocesses/__init__.py
scared/preprocesses/_base.py
scared/preprocesses/first_order.py
scared/preprocesses/high_order/__init__.py
scared/preprocesses/high_order/_base.py
scared/preprocesses/high_order/standard.py
scared/preprocesses/high_order/time_freq.py
scared/scalib/__init__.py
scared/scalib/analysis.py
scared/scalib/snr.py
scared/scalib/ttest.py
scared/selection_functions/__init__.py
scared/selection_functions/base.py
scared/selection_functions/guesses.py
scared/signal_processing/__init__.py
scared/signal_processing/base.py
scared/signal_processing/filters.py
scared/signal_processing/frequency_analysis.py
scared/signal_processing/moving_operators.py
scared/signal_processing/pattern_detection.py
scared/signal_processing/peaks_detection.py
scared/utils/__init__.py
scared/utils/fast_astype.py
scared/utils/inplace_dot_sum.py
scared/utils/misc.py
scared-1.2.8.dist-info/licenses/AUTHORS.md
scared-1.2.8.dist-info/licenses/LICENSE
scared-1.2.8.dist-info/METADATA
scared-1.2.8.dist-info/WHEEL
scared-1.2.8.dist-info/top_level.txt
scared-1.2.8.dist-info/RECORD
