Metadata-Version: 2.4
Name: scared
Version: 1.2.8
Summary: eshard scared Python library.
Author-email: eshard <contact@eshard.com>
License: LGPL-3.0
Project-URL: Homepage, https://www.eshard.com
Project-URL: Documentation, https://eshard.gitlab.io/scared
Keywords: scared
Classifier: Programming Language :: Python :: 3.11
Classifier: Programming Language :: Python :: 3.12
Classifier: Programming Language :: Python :: 3.13
Classifier: Intended Audience :: Developers
Classifier: Operating System :: OS Independent
Classifier: Topic :: Software Development
Requires-Python: >=3.11.0
License-File: LICENSE
License-File: AUTHORS.md
Requires-Dist: numba
Requires-Dist: numpy>=2.0.0
Requires-Dist: estraces>=1.9.4
Requires-Dist: psutil
Requires-Dist: scipy
Provides-Extra: test
Requires-Dist: pycryptodome; extra == "test"
Requires-Dist: pytest; extra == "test"
Requires-Dist: pytest-cov; extra == "test"
Requires-Dist: pytest-mock; extra == "test"
Provides-Extra: test-scalib
Requires-Dist: pycryptodome; extra == "test-scalib"
Requires-Dist: pytest; extra == "test-scalib"
Requires-Dist: pytest-cov; extra == "test-scalib"
Requires-Dist: pytest-mock; extra == "test-scalib"
Requires-Dist: scalib; extra == "test-scalib"
Dynamic: license-file
